[
  {
    "model": "pecore",
    "ckpt": "pecore-OOD_P_b1-v9-epoch=01-val_accuracy=1.00-v1.ckpt",
    "score": "individual",
    "accuracy": 0.3088235294117647
  },
  {
    "model": "pecore",
    "ckpt": "pecore-OOD_P_b1-v9-epoch=01-val_accuracy=1.00-v1.ckpt",
    "score": "pairwise",
    "accuracy": 0.04411764705882353
  },
  {
    "model": "pecore",
    "ckpt": "pecore-OOD_P_b1-v9-epoch=01-val_accuracy=1.00-v1.ckpt",
    "score": "setwise",
    "accuracy": 0.0
  },
  {
    "model": "pecore",
    "ckpt": "pecore-OOD_P_b1-v9-epoch=01-val_accuracy=1.00-v1.ckpt",
    "score": "similarity",
    "accuracy": 0.7634803921568627
  }
]