{
  "relation": "right",
  "obj1": {
    "shape": "Sphere",
    "color": [
      1.0,
      0.9333333333333333,
      0.2,
      1.0
    ],
    "material": "Rubber",
    "size": 0.35,
    "3d_coords": [
      -1.5185362100601196,
      2.0915369987487793,
      0.35
    ]
  },
  "obj2": {
    "shape": "Cone",
    "color": [
      0.3411764705882353,
      0.3411764705882353,
      0.3411764705882353,
      1.0
    ],
    "material": "Rubber",
    "size": 0.7,
    "3d_coords": [
      2.1741905212402344,
      0.5386407375335693,
      0.7
    ]
  },
  "clevr_source": {
    "obj1_index": -1,
    "obj2_index": -1
  }
}