{
  "relation": "left",
  "obj1": {
    "shape": "SmoothCube_v2",
    "color": [
      0.11372549019607843,
      0.4117647058823529,
      0.0784313725490196,
      1.0
    ],
    "material": "Rubber",
    "size": 0.35,
    "3d_coords": [
      1.8782533407211304,
      -1.7199190855026245,
      0.35
    ]
  },
  "obj2": {
    "shape": "SmoothCube_v2",
    "color": [
      0.16470588235294117,
      0.29411764705882354,
      0.8431372549019608,
      1.0
    ],
    "material": "Rubber",
    "size": 0.7,
    "3d_coords": [
      -1.8123761415481567,
      2.852450370788574,
      0.7
    ]
  },
  "clevr_source": {
    "obj1_index": -1,
    "obj2_index": -1
  }
}