{
  "relation": "right",
  "obj1": {
    "shape": "Sphere",
    "color": [
      0.1607843137254902,
      0.8156862745098039,
      0.8156862745098039,
      1.0
    ],
    "material": "Rubber",
    "size": 0.7,
    "3d_coords": [
      2.8166685104370117,
      0.5171544551849365,
      0.7
    ]
  },
  "obj2": {
    "shape": "Cone",
    "color": [
      0.6784313725490196,
      0.13725490196078433,
      0.13725490196078433,
      1.0
    ],
    "material": "Rubber",
    "size": 0.7,
    "3d_coords": [
      -0.5993116497993469,
      1.316075086593628,
      0.7
    ]
  },
  "clevr_source": {
    "obj1_index": -1,
    "obj2_index": -1
  }
}