{
  "relation": "right",
  "obj1": {
    "shape": "SmoothCube_v2",
    "color": [
      0.3411764705882353,
      0.3411764705882353,
      0.3411764705882353,
      1.0
    ],
    "material": "Rubber",
    "size": 0.35,
    "3d_coords": [
      1.8952656984329224,
      -1.5401349067687988,
      0.35
    ]
  },
  "obj2": {
    "shape": "Cone",
    "color": [
      0.1607843137254902,
      0.8156862745098039,
      0.8156862745098039,
      1.0
    ],
    "material": "Rubber",
    "size": 0.7,
    "3d_coords": [
      1.5285817384719849,
      1.9945237636566162,
      0.7
    ]
  },
  "clevr_source": {
    "obj1_index": -1,
    "obj2_index": -1
  }
}