{
  "relation": "behind",
  "obj1": {
    "shape": "SmoothCube_v2",
    "color": [
      1.0,
      0.9333333333333333,
      0.2,
      1.0
    ],
    "material": "Rubber",
    "size": 0.35,
    "3d_coords": [
      -2.1565990447998047,
      2.2062106132507324,
      0.3499999940395355
    ]
  },
  "obj2": {
    "shape": "Cone",
    "color": [
      1.0,
      0.9333333333333333,
      0.2,
      1.0
    ],
    "material": "Rubber",
    "size": 0.35,
    "3d_coords": [
      1.4339704513549805,
      2.6829285621643066,
      0.3499999940395355
    ]
  }
}