{
  "relation": "front",
  "obj1": {
    "shape": "SmoothCylinder",
    "color": [
      0.1607843137254902,
      0.8156862745098039,
      0.8156862745098039,
      1.0
    ],
    "material": "Rubber",
    "size": 0.35,
    "3d_coords": [
      2.4601593017578125,
      -0.047659121453762054,
      0.3499999940395355
    ]
  },
  "obj2": {
    "shape": "Sphere",
    "color": [
      0.1607843137254902,
      0.8156862745098039,
      0.8156862745098039,
      1.0
    ],
    "material": "Rubber",
    "size": 0.7,
    "3d_coords": [
      0.5427272915840149,
      2.4844045639038086,
      0.699999988079071
    ]
  }
}