{
  "relation": "front",
  "obj1": {
    "shape": "SmoothCylinder",
    "color": [
      0.5058823529411764,
      0.14901960784313725,
      0.7529411764705882,
      1.0
    ],
    "material": "Rubber",
    "size": 0.7,
    "3d_coords": [
      2.7848856449127197,
      1.3038761615753174,
      0.699999988079071
    ]
  },
  "obj2": {
    "shape": "Cone",
    "color": [
      0.3411764705882353,
      0.3411764705882353,
      0.3411764705882353,
      1.0
    ],
    "material": "Rubber",
    "size": 0.7,
    "3d_coords": [
      -0.2820329964160919,
      1.753179907798767,
      0.699999988079071
    ]
  }
}