{
  "relation": "right",
  "obj1": {
    "shape": "SmoothCube_v2",
    "color": [
      1.0,
      0.9333333333333333,
      0.2,
      1.0
    ],
    "material": "Rubber",
    "size": 0.35,
    "3d_coords": [
      0.10468563437461853,
      2.490044355392456,
      0.3499999940395355
    ]
  },
  "obj2": {
    "shape": "Cone",
    "color": [
      0.16470588235294117,
      0.29411764705882354,
      0.8431372549019608,
      1.0
    ],
    "material": "Rubber",
    "size": 0.35,
    "3d_coords": [
      -1.7606819868087769,
      -2.42622971534729,
      0.3499999940395355
    ]
  }
}