{
  "relation": "left",
  "obj1": {
    "shape": "SmoothCube_v2",
    "color": [
      0.5058823529411764,
      0.2901960784313726,
      0.09803921568627451,
      1.0
    ],
    "material": "Rubber",
    "size": 0.7,
    "3d_coords": [
      -2.105513095855713,
      0.9286763072013855,
      0.699999988079071
    ]
  },
  "obj2": {
    "shape": "Cone",
    "color": [
      0.5058823529411764,
      0.14901960784313725,
      0.7529411764705882,
      1.0
    ],
    "material": "Rubber",
    "size": 0.7,
    "3d_coords": [
      1.0679214000701904,
      2.2216506004333496,
      0.699999988079071
    ]
  }
}