{
  "relation": "behind",
  "obj1": {
    "shape": "SmoothCylinder",
    "color": [
      0.3411764705882353,
      0.3411764705882353,
      0.3411764705882353,
      1.0
    ],
    "material": "Rubber",
    "size": 0.35,
    "3d_coords": [
      -0.5302125215530396,
      0.48579904437065125,
      0.3499999940395355
    ]
  },
  "obj2": {
    "shape": "SmoothCylinder",
    "color": [
      1.0,
      0.9333333333333333,
      0.2,
      1.0
    ],
    "material": "Rubber",
    "size": 0.35,
    "3d_coords": [
      2.3337743282318115,
      -2.558872699737549,
      0.3499999940395355
    ]
  }
}