{
  "relation": "behind",
  "obj1": {
    "shape": "SmoothCube_v2",
    "color": [
      0.5058823529411764,
      0.2901960784313726,
      0.09803921568627451,
      1.0
    ],
    "material": "Rubber",
    "size": 0.7,
    "3d_coords": [
      -2.7717952728271484,
      2.3327064514160156,
      0.699999988079071
    ]
  },
  "obj2": {
    "shape": "SmoothCube_v2",
    "color": [
      0.6784313725490196,
      0.13725490196078433,
      0.13725490196078433,
      1.0
    ],
    "material": "Rubber",
    "size": 0.35,
    "3d_coords": [
      0.12826354801654816,
      1.6790779829025269,
      0.3499999940395355
    ]
  }
}