{
  "relation": "right",
  "obj1": {
    "shape": "SmoothCylinder",
    "color": [
      0.1607843137254902,
      0.8156862745098039,
      0.8156862745098039,
      1.0
    ],
    "material": "Rubber",
    "size": 0.35,
    "3d_coords": [
      -1.1141717433929443,
      -0.6297463178634644,
      0.35
    ]
  },
  "obj2": {
    "shape": "Cone",
    "color": [
      0.5058823529411764,
      0.14901960784313725,
      0.7529411764705882,
      1.0
    ],
    "material": "Rubber",
    "size": 0.35,
    "3d_coords": [
      -1.7622368335723877,
      2.8591806888580322,
      0.35
    ]
  },
  "clevr_source": {
    "obj1_index": -1,
    "obj2_index": -1
  }
}