{
  "relation": "left",
  "obj1": {
    "shape": "Sphere",
    "color": [
      0.3411764705882353,
      0.3411764705882353,
      0.3411764705882353,
      1.0
    ],
    "material": "Rubber",
    "size": 0.7,
    "3d_coords": [
      -0.49061012268066406,
      -0.3845113217830658,
      0.699999988079071
    ]
  },
  "obj2": {
    "shape": "Sphere",
    "color": [
      1.0,
      0.9333333333333333,
      0.2,
      1.0
    ],
    "material": "Rubber",
    "size": 0.7,
    "3d_coords": [
      0.9835874438285828,
      -2.8924050331115723,
      0.699999988079071
    ]
  },
  "clevr_source": {
    "obj1_index": -1,
    "obj2_index": -1
  }
}