{
  "relation": "right",
  "obj1": {
    "shape": "SmoothCylinder",
    "color": [
      0.3411764705882353,
      0.3411764705882353,
      0.3411764705882353,
      1.0
    ],
    "material": "Rubber",
    "size": 0.7,
    "3d_coords": [
      2.2985122203826904,
      -2.847125291824341,
      0.699999988079071
    ]
  },
  "obj2": {
    "shape": "Sphere",
    "color": [
      0.3411764705882353,
      0.3411764705882353,
      0.3411764705882353,
      1.0
    ],
    "material": "Rubber",
    "size": 0.35,
    "3d_coords": [
      -1.7502586841583252,
      -2.1226558685302734,
      0.3499999940395355
    ]
  }
}