{
  "relation": "left",
  "obj1": {
    "shape": "SmoothCylinder",
    "color": [
      0.5058823529411764,
      0.14901960784313725,
      0.7529411764705882,
      1.0
    ],
    "material": "Rubber",
    "size": 0.7,
    "3d_coords": [
      0.9251531362533569,
      -2.493969440460205,
      0.699999988079071
    ]
  },
  "obj2": {
    "shape": "Sphere",
    "color": [
      0.3411764705882353,
      0.3411764705882353,
      0.3411764705882353,
      1.0
    ],
    "material": "Rubber",
    "size": 0.35,
    "3d_coords": [
      0.6072514057159424,
      0.6336149573326111,
      0.3499999940395355
    ]
  }
}