{
  "relation": "front",
  "obj1": {
    "shape": "SmoothCube_v2",
    "color": [
      0.5058823529411764,
      0.14901960784313725,
      0.7529411764705882,
      1.0
    ],
    "material": "Rubber",
    "size": 0.35,
    "3d_coords": [
      2.762049913406372,
      -1.6666743755340576,
      0.3499999940395355
    ]
  },
  "obj2": {
    "shape": "Sphere",
    "color": [
      0.11372549019607843,
      0.4117647058823529,
      0.0784313725490196,
      1.0
    ],
    "material": "Rubber",
    "size": 0.35,
    "3d_coords": [
      -2.6991353034973145,
      -0.475506454706192,
      0.3499999940395355
    ]
  }
}