{
  "relation": "right",
  "obj1": {
    "shape": "SmoothCylinder",
    "color": [
      0.5058823529411764,
      0.14901960784313725,
      0.7529411764705882,
      1.0
    ],
    "material": "Rubber",
    "size": 0.7,
    "3d_coords": [
      0.5377023816108704,
      2.0044493675231934,
      0.699999988079071
    ]
  },
  "obj2": {
    "shape": "Cone",
    "color": [
      0.6784313725490196,
      0.13725490196078433,
      0.13725490196078433,
      1.0
    ],
    "material": "Rubber",
    "size": 0.7,
    "3d_coords": [
      1.50743567943573,
      -0.08501219749450684,
      0.699999988079071
    ]
  }
}