{
  "relation": "behind",
  "obj1": {
    "shape": "SmoothCylinder",
    "color": [
      0.5058823529411764,
      0.14901960784313725,
      0.7529411764705882,
      1.0
    ],
    "material": "Rubber",
    "size": 0.35,
    "3d_coords": [
      -1.3740400075912476,
      -2.4495627880096436,
      0.3499999940395355
    ]
  },
  "obj2": {
    "shape": "Cone",
    "color": [
      1.0,
      0.9333333333333333,
      0.2,
      1.0
    ],
    "material": "Rubber",
    "size": 0.35,
    "3d_coords": [
      2.1186013221740723,
      -1.2390185594558716,
      0.3499999940395355
    ]
  }
}