{
  "relation": "front",
  "obj1": {
    "shape": "Sphere",
    "color": [
      0.3411764705882353,
      0.3411764705882353,
      0.3411764705882353,
      1.0
    ],
    "material": "Rubber",
    "size": 0.35,
    "3d_coords": [
      -0.12402704358100891,
      0.5862659215927124,
      0.3499999940395355
    ]
  },
  "obj2": {
    "shape": "Cone",
    "color": [
      1.0,
      0.9333333333333333,
      0.2,
      1.0
    ],
    "material": "Rubber",
    "size": 0.35,
    "3d_coords": [
      0.3963715136051178,
      2.385289192199707,
      0.3499999940395355
    ]
  },
  "clevr_source": {
    "obj1_index": -1,
    "obj2_index": -1
  }
}