{
  "relation": "left",
  "obj1": {
    "shape": "SmoothCube_v2",
    "color": [
      0.3411764705882353,
      0.3411764705882353,
      0.3411764705882353,
      1.0
    ],
    "material": "Rubber",
    "size": 0.35,
    "3d_coords": [
      -0.32520592212677,
      -1.7504198551177979,
      0.3499999940395355
    ]
  },
  "obj2": {
    "shape": "Sphere",
    "color": [
      0.11372549019607843,
      0.4117647058823529,
      0.0784313725490196,
      1.0
    ],
    "material": "Rubber",
    "size": 0.7,
    "3d_coords": [
      2.1147074699401855,
      -1.7168827056884766,
      0.699999988079071
    ]
  }
}