{
  "relation": "right",
  "obj1": {
    "shape": "SmoothCylinder",
    "color": [
      1.0,
      0.9333333333333333,
      0.2,
      1.0
    ],
    "material": "Rubber",
    "size": 0.35,
    "3d_coords": [
      2.052332878112793,
      0.9123695492744446,
      0.3499999940395355
    ]
  },
  "obj2": {
    "shape": "Cone",
    "color": [
      1.0,
      0.9333333333333333,
      0.2,
      1.0
    ],
    "material": "Rubber",
    "size": 0.35,
    "3d_coords": [
      0.22166772186756134,
      1.7808319330215454,
      0.3499999940395355
    ]
  },
  "clevr_source": {
    "obj1_index": -1,
    "obj2_index": -1
  }
}