{
  "relation": "behind",
  "obj1": {
    "shape": "SmoothCube_v2",
    "color": [
      0.6784313725490196,
      0.13725490196078433,
      0.13725490196078433,
      1.0
    ],
    "material": "Rubber",
    "size": 0.35,
    "3d_coords": [
      2.5839414596557617,
      2.995056629180908,
      0.35
    ]
  },
  "obj2": {
    "shape": "SmoothCube_v2",
    "color": [
      0.11372549019607843,
      0.4117647058823529,
      0.0784313725490196,
      1.0
    ],
    "material": "Rubber",
    "size": 0.7,
    "3d_coords": [
      -1.6995368003845215,
      -2.816896915435791,
      0.7
    ]
  },
  "clevr_source": {
    "obj1_index": -1,
    "obj2_index": -1
  }
}