{
  "relation": "behind",
  "obj1": {
    "shape": "SmoothCylinder",
    "color": [
      0.3411764705882353,
      0.3411764705882353,
      0.3411764705882353,
      1.0
    ],
    "material": "Rubber",
    "size": 0.7,
    "3d_coords": [
      2.7310242652893066,
      1.975563645362854,
      0.699999988079071
    ]
  },
  "obj2": {
    "shape": "Cone",
    "color": [
      0.6784313725490196,
      0.13725490196078433,
      0.13725490196078433,
      1.0
    ],
    "material": "Rubber",
    "size": 0.7,
    "3d_coords": [
      -1.90385103225708,
      2.8590404987335205,
      0.699999988079071
    ]
  },
  "clevr_source": {
    "obj1_index": -1,
    "obj2_index": -1
  }
}