{
  "relation": "right",
  "obj1": {
    "shape": "SmoothCube_v2",
    "color": [
      0.1607843137254902,
      0.8156862745098039,
      0.8156862745098039,
      1.0
    ],
    "material": "Rubber",
    "size": 0.7,
    "3d_coords": [
      -0.08370829373598099,
      0.533943772315979,
      0.699999988079071
    ]
  },
  "obj2": {
    "shape": "SmoothCylinder",
    "color": [
      0.3411764705882353,
      0.3411764705882353,
      0.3411764705882353,
      1.0
    ],
    "material": "Rubber",
    "size": 0.35,
    "3d_coords": [
      -0.6372737884521484,
      -2.8002333641052246,
      0.3499999940395355
    ]
  }
}