{
  "relation": "right",
  "obj1": {
    "shape": "SmoothCylinder",
    "color": [
      0.3411764705882353,
      0.3411764705882353,
      0.3411764705882353,
      1.0
    ],
    "material": "Rubber",
    "size": 0.7,
    "3d_coords": [
      2.9573111534118652,
      2.2788729667663574,
      0.699999988079071
    ]
  },
  "obj2": {
    "shape": "Sphere",
    "color": [
      0.1607843137254902,
      0.8156862745098039,
      0.8156862745098039,
      1.0
    ],
    "material": "Rubber",
    "size": 0.7,
    "3d_coords": [
      -1.0843974351882935,
      -1.5977287292480469,
      0.699999988079071
    ]
  }
}