{
  "relation": "behind",
  "obj1": {
    "shape": "Sphere",
    "color": [
      1.0,
      0.9333333333333333,
      0.2,
      1.0
    ],
    "material": "Rubber",
    "size": 0.7,
    "3d_coords": [
      -2.7174220085144043,
      1.4899157285690308,
      0.699999988079071
    ]
  },
  "obj2": {
    "shape": "Cone",
    "color": [
      0.3411764705882353,
      0.3411764705882353,
      0.3411764705882353,
      1.0
    ],
    "material": "Rubber",
    "size": 0.35,
    "3d_coords": [
      -0.635901689529419,
      0.9713298678398132,
      0.3499999940395355
    ]
  }
}