{
  "relation": "behind",
  "obj1": {
    "shape": "SmoothCube_v2",
    "color": [
      0.16470588235294117,
      0.29411764705882354,
      0.8431372549019608,
      1.0
    ],
    "material": "Rubber",
    "size": 0.7,
    "3d_coords": [
      -1.502267599105835,
      2.8377912044525146,
      0.699999988079071
    ]
  },
  "obj2": {
    "shape": "Cone",
    "color": [
      0.5058823529411764,
      0.2901960784313726,
      0.09803921568627451,
      1.0
    ],
    "material": "Rubber",
    "size": 0.7,
    "3d_coords": [
      2.1435084342956543,
      2.0816659927368164,
      0.699999988079071
    ]
  }
}