{
  "relation": "right",
  "obj1": {
    "shape": "SmoothCylinder",
    "color": [
      0.6784313725490196,
      0.13725490196078433,
      0.13725490196078433,
      1.0
    ],
    "material": "Rubber",
    "size": 0.7,
    "3d_coords": [
      1.975401759147644,
      0.18283945322036743,
      0.699999988079071
    ]
  },
  "obj2": {
    "shape": "Sphere",
    "color": [
      0.6784313725490196,
      0.13725490196078433,
      0.13725490196078433,
      1.0
    ],
    "material": "Rubber",
    "size": 0.7,
    "3d_coords": [
      0.9764842987060547,
      -1.826008915901184,
      0.699999988079071
    ]
  }
}