{
  "relation": "front",
  "obj1": {
    "shape": "SmoothCube_v2",
    "color": [
      0.6784313725490196,
      0.13725490196078433,
      0.13725490196078433,
      1.0
    ],
    "material": "Rubber",
    "size": 0.7,
    "3d_coords": [
      2.1693806648254395,
      1.3650081157684326,
      0.7
    ]
  },
  "obj2": {
    "shape": "SmoothCube_v2",
    "color": [
      0.6784313725490196,
      0.13725490196078433,
      0.13725490196078433,
      1.0
    ],
    "material": "Rubber",
    "size": 0.7,
    "3d_coords": [
      2.8178224563598633,
      -1.3882646560668945,
      0.7
    ]
  },
  "clevr_source": {
    "obj1_index": -1,
    "obj2_index": -1
  }
}