{
  "relation": "front",
  "obj1": {
    "shape": "Sphere",
    "color": [
      0.5058823529411764,
      0.14901960784313725,
      0.7529411764705882,
      1.0
    ],
    "material": "Rubber",
    "size": 0.7,
    "3d_coords": [
      -1.1488142013549805,
      -2.88049054145813,
      0.7
    ]
  },
  "obj2": {
    "shape": "Cone",
    "color": [
      0.5058823529411764,
      0.14901960784313725,
      0.7529411764705882,
      1.0
    ],
    "material": "Rubber",
    "size": 0.35,
    "3d_coords": [
      -1.9289370775222778,
      1.3320544958114624,
      0.35
    ]
  },
  "clevr_source": {
    "obj1_index": -1,
    "obj2_index": -1
  }
}