{
  "relation": "left",
  "obj1": {
    "shape": "SmoothCylinder",
    "color": [
      0.3411764705882353,
      0.3411764705882353,
      0.3411764705882353,
      1.0
    ],
    "material": "Rubber",
    "size": 0.7,
    "3d_coords": [
      -0.6730929613113403,
      -1.9873063564300537,
      0.699999988079071
    ]
  },
  "obj2": {
    "shape": "Sphere",
    "color": [
      0.11372549019607843,
      0.4117647058823529,
      0.0784313725490196,
      1.0
    ],
    "material": "Rubber",
    "size": 0.7,
    "3d_coords": [
      0.2078472524881363,
      2.422856330871582,
      0.699999988079071
    ]
  }
}