{
  "relation": "behind",
  "obj1": {
    "shape": "SmoothCylinder",
    "color": [
      0.3411764705882353,
      0.3411764705882353,
      0.3411764705882353,
      1.0
    ],
    "material": "Rubber",
    "size": 0.7,
    "3d_coords": [
      -2.5532097816467285,
      1.6393781900405884,
      0.699999988079071
    ]
  },
  "obj2": {
    "shape": "Cone",
    "color": [
      1.0,
      0.9333333333333333,
      0.2,
      1.0
    ],
    "material": "Rubber",
    "size": 0.7,
    "3d_coords": [
      -0.2585728168487549,
      0.5090189576148987,
      0.699999988079071
    ]
  }
}