{
  "relation": "right",
  "obj1": {
    "shape": "SmoothCylinder",
    "color": [
      0.5058823529411764,
      0.14901960784313725,
      0.7529411764705882,
      1.0
    ],
    "material": "Rubber",
    "size": 0.7,
    "3d_coords": [
      2.0237154960632324,
      2.748322010040283,
      0.699999988079071
    ]
  },
  "obj2": {
    "shape": "Sphere",
    "color": [
      0.5058823529411764,
      0.14901960784313725,
      0.7529411764705882,
      1.0
    ],
    "material": "Rubber",
    "size": 0.35,
    "3d_coords": [
      0.5197397470474243,
      -0.7735146284103394,
      0.3499999940395355
    ]
  }
}